adjustapi/__init__.py
adjustapi/api.py
adjustapi/model.py
python_adjust-1.0.3.dist-info/LICENSE
python_adjust-1.0.3.dist-info/METADATA
python_adjust-1.0.3.dist-info/WHEEL
python_adjust-1.0.3.dist-info/top_level.txt
python_adjust-1.0.3.dist-info/RECORD
