Metadata-Version: 2.1
Name: python-adjust
Version: 1.0.3
Summary: Adjust.com REST API python implementation
Home-page: https://github.com/sann05/python-adjust
Author: Aliaksandr Sheliutsin
Author-email: 
License: MIT
Keywords: adjust mobile measurement kpi api
Platform: UNKNOWN
Classifier: Intended Audience :: Developers
Classifier: License :: OSI Approved :: MIT License
Classifier: Operating System :: OS Independent
Classifier: Programming Language :: Python :: 3
Classifier: Programming Language :: Python :: 3.5
Classifier: Programming Language :: Python :: 3.6
Classifier: Programming Language :: Python :: 3.7
Classifier: Programming Language :: Python :: 3.8
Classifier: Programming Language :: Python
Classifier: Topic :: Software Development :: Libraries :: Python Modules
Requires-Python: >=3.5
License-File: LICENSE
Requires-Dist: pandas (>=0.25.3)
Requires-Dist: requests (>=2.23.0)
Requires-Dist: marshmallow-dataclass (==7.5.2)
